.DS_Store
pyiotdevice/__init__.py
pyiotdevice/const.py
pyiotdevice/crypto_utils.py
pyiotdevice/custom_exceptions.py
pyiotdevice/device_utils.py
pyiotdevice/get_hostname.py
pyiotdevice/get_thing_info.py
pyiotdevice/get_thing_status.py
pyiotdevice/mapping.py
pyiotdevice/send_ac_command.py
pyiotdevice/socket_utils.py
pyiotdevice-1.0.20.dist-info/LICENSE
pyiotdevice-1.0.20.dist-info/METADATA
pyiotdevice-1.0.20.dist-info/WHEEL
pyiotdevice-1.0.20.dist-info/top_level.txt
pyiotdevice-1.0.20.dist-info/RECORD
